markup_tg_logger/__init__.py
markup_tg_logger/config.py
markup_tg_logger/defaults.py
markup_tg_logger/exceptions.py
markup_tg_logger/handler.py
markup_tg_logger/py.typed
markup_tg_logger/resolve_object_from_config.py
markup_tg_logger/types.py
markup_tg_logger/formatters/__init__.py
markup_tg_logger/formatters/base.py
markup_tg_logger/formatters/escape.py
markup_tg_logger/formatters/html.py
markup_tg_logger/interfaces/__init__.py
markup_tg_logger/interfaces/message_splitter.py
markup_tg_logger/interfaces/notifier.py
markup_tg_logger/interfaces/telegram_sender.py
markup_tg_logger/message_splitters/__init__.py
markup_tg_logger/message_splitters/base.py
markup_tg_logger/message_splitters/factory.py
markup_tg_logger/message_splitters/html.py
markup_tg_logger/notifiers/__init__.py
markup_tg_logger/notifiers/level.py
markup_tg_logger/notifiers/static.py
markup_tg_logger/telegram_senders/__init__.py
markup_tg_logger/telegram_senders/http_client.py
markup_tg_logger/telegram_senders/requests.py
markup_tg_logger-1.1.0.dist-info/METADATA
markup_tg_logger-1.1.0.dist-info/WHEEL
markup_tg_logger-1.1.0.dist-info/licenses/LICENSE
markup_tg_logger-1.1.0.dist-info/RECORD
