Metadata-Version: 2.4
Name: markup-tg-logger
Version: 1.1.0
Summary: Flexible integration of logging module and Telegram Bot Api with HTML support
Project-URL: Github, https://github.com/korandr/markup-tg-logger
Project-URL: Documentation, https://github.com/korandr/markup-tg-logger
Author-email: korandr <andrey.korovyansky@gmail.com>
License-Expression: MIT
License-File: LICENSE
Keywords: HTML,Markdown,MarkdownV2,Telegram,logger,logging
Classifier: Development Status :: 5 - Production/Stable
Classifier: Intended Audience :: Developers
Classifier: License :: OSI Approved :: MIT License
Classifier: Operating System :: OS Independent
Classifier: Programming Language :: Python :: 3
Classifier: Programming Language :: Python :: 3.12
Classifier: Programming Language :: Python :: 3.13
Classifier: Topic :: Communications :: Chat
Classifier: Topic :: Documentation
Classifier: Topic :: System :: Logging
Classifier: Topic :: Text Processing :: Markup
Classifier: Topic :: Text Processing :: Markup :: HTML
Classifier: Topic :: Text Processing :: Markup :: Markdown
Requires-Python: >=3.12
Provides-Extra: requests
Requires-Dist: requests; extra == 'requests'
